LAMP/__init__.py
LAMP/api/__init__.py
LAMP/api/activity_api.py
LAMP/api/activity_event_api.py
LAMP/api/activity_spec_api.py
LAMP/api/api_api.py
LAMP/api/credential_api.py
LAMP/api/participant_api.py
LAMP/api/researcher_api.py
LAMP/api/sensor_api.py
LAMP/api/sensor_event_api.py
LAMP/api/sensor_spec_api.py
LAMP/api/study_api.py
LAMP/api/type_api.py
LAMP/api_client.py
LAMP/configuration.py
LAMP/exceptions.py
LAMP/model_utils.py
LAMP/models/__init__.py
LAMP/models/access_citation.py
LAMP/models/activity.py
LAMP/models/activity_event.py
LAMP/models/activity_spec.py
LAMP/models/credential.py
LAMP/models/document.py
LAMP/models/duration_interval.py
LAMP/models/duration_interval_legacy.py
LAMP/models/dynamic_attachment.py
LAMP/models/error.py
LAMP/models/metadata.py
LAMP/models/participant.py
LAMP/models/researcher.py
LAMP/models/sensor.py
LAMP/models/sensor_event.py
LAMP/models/sensor_spec.py
LAMP/models/study.py
LAMP/models/temporal_slice.py
LAMP/rest.py
lamp_core-2021.10.4.dist-info/LICENSE
lamp_core-2021.10.4.dist-info/WHEEL
lamp_core-2021.10.4.dist-info/METADATA
lamp_core-2021.10.4.dist-info/RECORD
