Metadata-Version: 2.1
Name: lamp-core
Version: 2021.10.4
Summary: The LAMP Platform API.
Home-page: https://docs.lamp.digital/
License: BSD-3-Clause
Keywords: LAMP API
Author: Division of Digital Psychiatry at Beth Israel Deaconess Medical Center
Author-email: team@digitalpsych.org
Requires-Python: >=3.0,<4.0
Classifier: License :: OSI Approved :: BSD License
Classifier: Programming Language :: Python :: 3
Classifier: Programming Language :: Python :: 3.4
Classifier: Programming Language :: Python :: 3.5
Classifier: Programming Language :: Python :: 3.6
Classifier: Programming Language :: Python :: 3.7
Classifier: Programming Language :: Python :: 3.8
Classifier: Programming Language :: Python :: 3.9
Requires-Dist: certifi (>=14.05.14)
Requires-Dist: nulltype (>=2.3.1,<3.0.0)
Requires-Dist: python-dateutil (>=2.5.3)
Requires-Dist: urllib3 (>=1.15.1)
Project-URL: Bug Tracker, https://github.com/BIDMCDigitalPsychiatry/LAMP-platform/issues
Project-URL: Documentation, https://docs.lamp.digital/
Project-URL: Repository, https://github.com/BIDMCDigitalPsychiatry/LAMP-py
